[
  {
    "title": "DrawerType",
    "description": "Props for the ZenDrawer component",
    "category": "Drawer Components Props"
  },
  {
    "title": "ZenDrawer",
    "description": "A drawer component that can be opened from the left or right side of the screen. It is controlled by the useDrawer and useToggleDrawer hooks. Works on web and on mobile devices.",
    "category": "Drawer Components",
    "author": "Danilo Ramírez Mattey",
    "version": "1.0.0",
    "type": "Component",
    "access": "Public",
    "copyright": "No copyright",
    "order": "0",
    "example": [
      {
        "lang": "tsx",
        "code": "import { ZenDark,\n           ZenThemeProvider,\n           ZenDrawer,\n           ZenDrawerTitle,\n           ZenDrawerItem } from 'react-zen-ui';\n\n  export default function App() {\n\n     const DrawerItems = [\n         <ZenDrawerTitle title={'Main Menu'} key={'title'} />,\n         <ZenDrawerItem\n             label={'Home'}\n             key={'home'}\n             leftIcon={'home'}\n             onPress={() => navigation.navigate('Home' as never)}\n         />,\n         <ZenDrawerItem\n             label={'Theme'}\n             key={'theme'}\n             leftIcon={'settings'}\n             onPress={() => navigation.navigate('Theme' as never)}\n         />,\n         <ZenDrawerItem\n             label={'Drawer'}\n             key={'drawer'}\n             leftIcon={'settings'}\n             onPress={() => navigation.navigate('Drawer' as never)}\n         />,\n         <ZenDrawerTitle title={'Example elements'} key={'example_elements'} />,\n         <ZenDrawerItem\n             label={'Example Car'}\n             key={'example'}\n             leftIcon={'car'}\n             rightIcon={'truck'}\n         />,\n         <ZenDrawerItem\n             label={'Dimensional'}\n             key={'dimensional'}\n             leftIcon={'clock'}\n         />,\n     ];\n\n    const image = require('../assets/logo.png');\n\n    const headerComponent = (props: NativeStackHeaderProps) => (\n      <ZenHeader\n        automaticDrawerIcon={'menu'}\n        showBackButton={props.navigation.canGoBack()}\n        title={props.options.title as string}\n        goBack={()=>{ props.navigation.goBack(); }}\n        {...props}\n      />\n    );\n\n    return (\n         <ZenThemeProvider theme={ZenDark}>\n         <ZenDrawer\n             headerImage={image}\n             headerImageSize={275}\n             items={DrawerItems}\n         />\n          <Stack.Navigator\n            screenOptions={{\n              animation: 'default',\n              headerShown: true,\n              header: headerComponent,\n           }}\n          >\n              // OTHER STACK SCREEN ELEMENTS AND COMPONENTS HERE\n           </Stack.Navigator>\n         </ZenThemeProvider>\n     );\n   }",
        "closeLang": "tsx"
      }
    ],
    "params": [
      {
        "type": "string",
        "name": "position",
        "description": "The position of the drawer (left or right)"
      },
      {
        "type": "number",
        "name": "backgroundDimmed",
        "description": "Whether the background should be dimmed or not"
      },
      {
        "type": "string",
        "name": "backgroundColor",
        "description": "The color of the background when dimmed"
      },
      {
        "type": "Element",
        "name": "headerImage",
        "description": "An optional image to display at the top of the drawer"
      },
      {
        "type": "number",
        "name": "headerImageSize",
        "description": "The height of the header image"
      },
      {
        "type": "Elements[]",
        "name": "items",
        "description": "An array of React Elements to display as items in the drawer. Recommended to use ZenDrawerItem and ZenDrawerTitle components."
      },
      {
        "type": "number",
        "name": "sizeRatio",
        "description": "The size of the drawer as a ratio of the screen width"
      },
      {
        "type": "number",
        "name": "animationTime",
        "description": "The time in milliseconds for the open/close animation"
      }
    ],
    "errors": [
      {
        "type": "AnimationError",
        "description": "The animation time is invalid. It must be a positive number."
      }
    ]
  },
  {
    "title": "ZenDrawerItem",
    "description": "A single item for the ZenDrawer component",
    "category": "Drawer Components Props"
  },
  {
    "title": "ZenDrawerItem",
    "description": "A single item for the ZenDrawer component",
    "category": "Drawer Components",
    "author": "Danilo Ramírez Mattey",
    "version": "1.0.0",
    "see": [
      {
        "reference": "ZenDrawer"
      },
      {
        "reference": "ZenDrawerTitle"
      }
    ],
    "params": [
      {
        "type": "string",
        "name": "label",
        "description": "The label of the drawer item"
      },
      {
        "type": "string",
        "name": "leftIcon",
        "description": "The name of the left icon (from ZenIcon)"
      },
      {
        "type": "string",
        "name": "rightIcon",
        "description": "The name of the right icon (from ZenIcon)"
      },
      {
        "type": "function",
        "name": "onPress",
        "description": "The function to call when the item is pressed"
      },
      {
        "type": "boolean",
        "name": "arrow",
        "description": "Whether to show a right arrow icon"
      },
      {
        "type": "function",
        "name": "closeOnPress",
        "description": "Whether to close the drawer when the item is pressed"
      }
    ]
  },
  {
    "title": "ZenDrawerTitle",
    "description": "A title component for the ZenDrawer",
    "category": "Drawer Components Props"
  },
  {
    "title": "ZenDrawerTitle",
    "description": "A title component for the ZenDrawer",
    "category": "Drawer Components",
    "author": "Danilo Ramírez Mattey",
    "version": "1.0.0",
    "see": [
      {
        "reference": "ZenDrawer"
      },
      {
        "reference": "ZenDrawerItem"
      }
    ],
    "params": [
      {
        "type": "string",
        "name": "title",
        "description": "The title text to display"
      }
    ]
  },
  {
    "title": "ZenFloatingIconsType",
    "description": "Props for the ZenFloatingIcons component",
    "category": "Navigation Components Props"
  },
  {
    "title": "ZenFloatingIcons",
    "description": "A set of floating icon buttons that can be positioned at the bottom of the screen",
    "category": "Navigation Components",
    "author": "Danilo Ramírez Mattey",
    "version": "1.0.0",
    "link": [
      {
        "url": "https://reactnavigation.org/"
      }
    ],
    "example": [
      {
        "lang": "tsx",
        "code": "import { ZenDark, ZenThemeProvider, ZenFloatingIcons } from 'react-zen-ui';\n\nexport default function App() {\n\n   const menuButtons: any[] = [\n     {\n       icon: 'home',\n       type: 'primary',\n       onPress: () => navigation.navigate('Home' as never),\n     },\n     {\n       icon: 'settings',\n       type: 'secondary',\n       onPress: () => navigation.navigate('Theme' as never),\n     },\n     {\n       icon: 'apple',\n       type: 'success',\n       onPress: () => navigation.navigate('FloatingIcons' as never),\n     },\n   ];\n\n    const headerComponent = (props: NativeStackHeaderProps) => (\n      <ZenHeader\n        automaticDrawerIcon={'menu'}\n        showBackButton={props.navigation.canGoBack()}\n        title={props.options.title as string}\n        goBack={()=>{ props.navigation.goBack(); }}\n        {...props}\n      />\n    );\n\n    return (\n         <ZenThemeProvider theme={ZenDark}>\n            <ZenFloatingIcons buttons={menuButtons} size={'large'} />\n            <Stack.Navigator\n              screenOptions={{\n                animation: 'default',\n                headerShown: true,\n                header: headerComponent,\n             }}\n            >\n              // OTHER STACK SCREEN ELEMENTS AND COMPONENTS HERE\n           </Stack.Navigator>\n\n         </ZenThemeProvider>\n     );\n   }",
        "closeLang": "tsx"
      }
    ],
    "see": [
      {
        "reference": "Screen"
      },
      {
        "reference": "Layout"
      },
      {
        "reference": "ZenHeader"
      }
    ],
    "params": [
      {
        "type": "number",
        "name": "size",
        "description": "The size of the buttons (small, medium, large)"
      },
      {
        "type": "string",
        "name": "position",
        "description": "The position of the buttons (left, right, center)"
      },
      {
        "type": "Object",
        "name": "buttons",
        "description": "An array of button objects with icon, type and onPress function"
      }
    ]
  },
  {
    "title": "ZenHeaderProps",
    "description": "Props for the ZenHeader component",
    "category": "Navigation Components Props"
  },
  {
    "title": "ZenHeader",
    "description": "A simple header component that will adapt to the current theme and display a title and a back button if needed",
    "category": "Navigation Components",
    "author": "Danilo Ramírez Mattey",
    "version": "1.0.0",
    "link": [
      {
        "url": "https://github.com/danilor/zen-ui/blob/main/example/src/App.tsx#L93"
      },
      {
        "url": "https://reactnavigation.org/"
      }
    ],
    "example": [
      {
        "lang": "tsx",
        "code": "import { ZenDark, ZenThemeProvider } from 'react-zen-ui';\n\nexport default function App() {\n\n  const headerComponent = (props: NativeStackHeaderProps) => (\n    <ZenHeader\n      automaticDrawerIcon={'menu'}\n      showBackButton={props.navigation.canGoBack()}\n      title={props.options.title as string}\n      goBack={()=>{ props.navigation.goBack(); }}\n      {...props}\n    />\n  );\n\n  return (\n       <ZenThemeProvider theme={ZenDark}>\n        <Stack.Navigator\n          screenOptions={{\n            animation: 'default',\n            headerShown: true,\n            header: headerComponent,\n         }}\n        >\n            // OTHER STACK SCREEN ELEMENTS AND COMPONENTS HERE\n         </Stack.Navigator>\n       </ZenThemeProvider>\n   );\n }",
        "closeLang": "tsx"
      }
    ],
    "params": [
      {
        "type": "boolean",
        "name": "useTopSafeArea",
        "description": "Whether to use the top safe area or not"
      },
      {
        "type": "string",
        "name": "title",
        "description": "The title to display in the header"
      },
      {
        "type": "boolean",
        "name": "showBackButton",
        "description": "Whether to show the back button or not"
      },
      {
        "type": "string",
        "name": "rightIcon",
        "description": "The name of the right icon to display"
      },
      {
        "type": "function",
        "name": "onRightIconPress",
        "description": "The function to call when the right icon is pressed"
      },
      {
        "type": "Element",
        "name": "rightAccessory",
        "description": "Any React Element to show on the right side of the header"
      },
      {
        "type": "string",
        "name": "automaticDrawerIcon",
        "description": "If any string is indicated, it will show a drawer icon that will open the drawer when pressed"
      },
      {
        "type": "function",
        "name": "goBack",
        "description": "The function to call when the back button is pressed"
      },
      {
        "type": "string",
        "name": "goBackIcon",
        "description": "The name of the back icon to display"
      }
    ]
  },
  {
    "title": "CardHeaderProps",
    "description": "Props for the CardHeader component.",
    "category": "Structure Components Props"
  },
  {
    "title": "CardHeader",
    "description": "A simple header component for the Card component.",
    "category": "Structure Components",
    "author": "Danilo Ramírez Mattey",
    "version": "1.0.0",
    "see": [
      {
        "reference": "Card"
      }
    ],
    "params": [
      {
        "type": "string",
        "name": "title",
        "description": "The title of the card header."
      },
      {
        "type": "string",
        "name": "type",
        "description": "The theme type of the card header."
      },
      {
        "type": "Element",
        "name": "leftAccessory",
        "description": "The left accessory component of the card header."
      },
      {
        "type": "Element",
        "name": "rightAccessory",
        "description": "The right accessory component of the card header."
      }
    ]
  },
  {
    "title": "Card Footer Props",
    "description": "Props for the CardFooter component.",
    "category": "Structure Components Props"
  },
  {
    "title": "CardFooter",
    "description": "A simple footer component for the Card component.",
    "category": "Structure Components",
    "author": "Danilo Ramírez Mattey",
    "version": "1.0.0",
    "see": [
      {
        "reference": "Card"
      }
    ],
    "params": [
      {
        "type": "string",
        "name": "type",
        "description": "The theme type of the card footer."
      },
      {
        "type": "Element",
        "name": "children",
        "description": "The children components of the card footer."
      }
    ]
  },
  {
    "title": "CardProps",
    "description": "Props for the Card component.",
    "category": "Structure Components Props"
  },
  {
    "title": "Card",
    "description": "A simple card component to display content in a card-like container.",
    "category": "Structure Components",
    "author": "Danilo Ramírez Mattey",
    "version": "1.0.0",
    "see": [
      {
        "reference": "CardFooter"
      },
      {
        "reference": "CardHeader"
      }
    ],
    "params": [
      {
        "type": "Element",
        "name": "children",
        "description": "The content of the card."
      },
      {
        "type": "string",
        "name": "type",
        "description": "The theme type of the card."
      },
      {
        "type": "string",
        "name": "title",
        "description": "The title of the card."
      },
      {
        "type": "Element",
        "name": "headerLeftAccessory",
        "description": "The left accessory component of the card header."
      },
      {
        "type": "Element",
        "name": "headerRightAccessory",
        "description": "The right accessory component of the card header."
      },
      {
        "type": "string",
        "name": "backColor",
        "description": "We can overwrite the background color by passing a custom color here."
      },
      {
        "type": "Element",
        "name": "header",
        "description": "We can overwrite the header by passing a custom component here."
      },
      {
        "type": "Element",
        "name": "footer",
        "description": "We can use this parameter to add a footer component to the card. We recomend using the CardFooter component."
      }
    ]
  },
  {
    "title": "LayoutProps",
    "description": "Props for the Layout component.",
    "category": "Structure Components Props"
  },
  {
    "title": "Layout",
    "description": "A layout component that provides consistent padding and optional scrolling behavior.",
    "category": "Structure Components",
    "author": "Danilo Ramírez Mattey",
    "version": "1.0.0",
    "example": [
      {
        "lang": "tsx",
        "code": "import { Screen, Layout, ZenText } from 'react-zen-ui';\n\n  export default function ExampleComponent(){\n  return (\n    <Screen useTopSafeArea={false}>\n        <Layout scrollable={true}>\n           <ZenText align={'justify'}>\n           Lorem ipsum dolor sit amet, consectetur adipiscing elit.\n            Sed do eiusmod tempor incididunt ut\n            labore et dolore magna aliqua. Ut enim\n            ad minim veniam, quis nostrud exercitation ullamco laboris nisi ut aliquip\n            ex ea commodo consequat. Duis aute irure dolor in\n            reprehenderit in voluptate velit esse cillum dolore eu fugiat\n            nulla pariatur. Excepteur sint occaecat cupidatat non proident,\n            sunt in culpa qui officia deserunt mollit anim id est laborum.\n           </ZenText>\n        </Layout>\n    </Screen>\n );\n }",
        "closeLang": "tsx"
      }
    ],
    "see": [
      {
        "reference": "Screen"
      }
    ],
    "params": [
      {
        "type": "Element",
        "name": "children",
        "description": "The children components to be rendered within the layout."
      },
      {
        "type": "boolean",
        "name": "centered",
        "description": "Whether to center the children components."
      },
      {
        "type": "boolean",
        "name": "scrollable",
        "description": "Whether the layout should be scrollable."
      },
      {
        "type": "StyleSheet",
        "name": "style",
        "description": "Additional styles to apply to the layout."
      },
      {
        "type": "boolean",
        "name": "airBottom",
        "description": "Whether to add extra space at the bottom of the layout."
      }
    ]
  },
  {
    "title": "ScreenProps",
    "description": "Props for the Screen component.",
    "category": "Structure Components Props"
  },
  {
    "title": "Screen",
    "description": "The screen component should be used as the main container for every screen in the app. The idea behind it is to use it only once in the app, right after the application provider tag. It should take care of the status bar height, the bottom bar height (if there is one) and the keyboard height. This way, we can have a full screen experience even when the keyboard is open.",
    "category": "Structure Components",
    "author": "Danilo Ramírez Mattey",
    "version": "1.0.0",
    "example": [
      {
        "lang": "tsx",
        "code": "import { Screen, Layout, ZenText } from 'react-zen-ui';\n\n    export default function ExampleComponent(){\n      return (\n        <Screen useTopSafeArea={false}>\n            <Layout scrollable={true}>\n               <ZenText align={'justify'}>\n               Lorem ipsum dolor sit amet, consectetur adipiscing elit.\n                Sed do eiusmod tempor incididunt ut\n                labore et dolore magna aliqua. Ut enim\n                ad minim veniam, quis nostrud exercitation ullamco laboris nisi ut aliquip\n                ex ea commodo consequat. Duis aute irure dolor in\n                reprehenderit in voluptate velit esse cillum dolore eu fugiat\n                nulla pariatur. Excepteur sint occaecat cupidatat non proident,\n                sunt in culpa qui officia deserunt mollit anim id est laborum.\n               </ZenText>\n            </Layout>\n        </Screen>\n     );\n   }",
        "closeLang": "tsx"
      }
    ],
    "see": [
      {
        "reference": "ZenThemeProvider"
      },
      {
        "reference": "Layout"
      }
    ],
    "params": [
      {
        "type": "Element",
        "name": "children",
        "description": "The main content of the screen. It could be anything, including React elements."
      },
      {
        "type": "boolean",
        "name": "useTopSafeArea",
        "description": "If true, the screen will use the top safe area. This is useful when you have a full screen and not planing to use react navigator or other similar libraries that already take care of the top safe area. Default is false."
      },
      {
        "type": "number",
        "name": "extraBottomPadding",
        "description": "If you need to add extra padding to the bottom of the screen, you can use this prop. Default is 0."
      }
    ]
  },
  {
    "title": "TableProps",
    "description": "Props for the Table component.",
    "category": "Structure Components Props"
  },
  {
    "title": "Table",
    "description": "A simple table component that will help you to create a grid layout",
    "category": "Structure Components",
    "author": "Danilo Ramírez Mattey",
    "version": "1.0.0",
    "example": [
      {
        "lang": "tsx",
        "code": "import { Column, Row, Table, ZenText } from 'react-zen-ui';\n\n export default function TablesExample(){\n   return (\n   <>\n       <ZenText type={'h4'} paragraph={true} align={'left'}>\n       Tables\n       </ZenText>\n\n       <ZenText type={'p'} paragraph={true} align={'justify'}>\n       Simple table components to create grid layouts. It consists of a Table component\n       that wraps Row components, which in turn wrap Column components. You can enable borders\n       and customize their appearance.\n       </ZenText>\n\n       <ZenText type={'p'} paragraph={true} align={'left'}>\n       Bordered table:\n       </ZenText>\n\n       <Table>\n         <Row>\n           <Column border={true}>\n            <ZenText type={'p'} paragraph={false} align={'center'}>1,1</ZenText>\n           </Column>\n\n           <Column border={true}>\n            <ZenText type={'p'} paragraph={false} align={'center'}>1,2</ZenText>\n           </Column>\n\n           <Column border={true}>\n            <ZenText type={'p'} paragraph={false} align={'center'}>1,3</ZenText>\n           </Column>\n         </Row>\n         <Row>\n           <Column border={true}>\n            <ZenText type={'p'} paragraph={false} align={'center'}>2,1</ZenText>\n           </Column>\n\n           <Column border={true}>\n            <ZenText type={'p'} paragraph={false} align={'center'}>2,2</ZenText>\n           </Column>\n\n           <Column border={true}>\n            <ZenText type={'p'} paragraph={false} align={'center'}>2,3</ZenText>\n           </Column>\n         </Row>\n         <Row>\n           <Column border={true}>\n            <ZenText type={'p'} paragraph={false} align={'center'}>3,1</ZenText>\n           </Column>\n\n           <Column border={true}>\n            <ZenText type={'p'} paragraph={false} align={'center'}>3,2</ZenText>\n           </Column>\n\n           <Column border={true}>\n            <ZenText type={'p'} paragraph={false} align={'center'}>3,3</ZenText>\n           </Column>\n\n         </Row>\n       </Table>\n\n\n   </>\n   );\n }",
        "closeLang": "tsx"
      }
    ],
    "see": [
      {
        "reference": "Row"
      },
      {
        "reference": "Column"
      }
    ],
    "params": [
      {
        "type": "StyleSheet",
        "name": "style",
        "description": "The additional styles to be added to the table. Default is null"
      },
      {
        "type": "Element",
        "name": "children",
        "description": "The child component of the table. This is required"
      },
      {
        "type": "boolean",
        "name": "border",
        "description": "The border of the table. Default is false"
      },
      {
        "type": "string",
        "name": "borderType",
        "description": "The border type of the table. Default is solid. Options are: solid, dotted, dashed"
      },
      {
        "type": "string",
        "name": "borderColor",
        "description": "The border color of the table. Default is the text color of the current theme"
      }
    ]
  },
  {
    "title": "Row",
    "description": "A simple row component that will help you to create a grid layout",
    "category": "Structure Components",
    "see": [
      {
        "reference": "Table"
      },
      {
        "reference": "Column"
      }
    ],
    "params": [
      {
        "type": "any",
        "name": "props",
        "description": "The props of the row component"
      },
      {
        "type": "Element",
        "name": "children",
        "description": "The child component of the row. This is required"
      },
      {
        "type": "StyleSheet",
        "name": "style",
        "description": "The additional styles to be added to the row. Default is null"
      }
    ]
  },
  {
    "title": "ColumnProps",
    "description": "Props for the Column component.",
    "category": "Structure Components Props",
    "params": [
      {
        "type": "Element",
        "name": "children",
        "description": "The child component of the column. This is required"
      },
      {
        "type": "StyleSheet",
        "name": "style",
        "description": "The additional styles to be added to the column. Default is null"
      },
      {
        "type": "boolean",
        "name": "border",
        "description": "The border of the column. Default is false"
      },
      {
        "type": "string",
        "name": "borderType",
        "description": "The border type of the column. Default is solid. Options are: solid, dotted, dashed"
      },
      {
        "type": "string",
        "name": "borderColor",
        "description": "The border color of the column. Default is the text color of the current theme"
      },
      {
        "type": "number",
        "name": "span",
        "description": "The number of columns to span. Default is 1"
      }
    ]
  },
  {
    "title": "Column",
    "description": "A simple column component that will help you to create a grid layout",
    "category": "Structure Components",
    "see": [
      {
        "reference": "Table"
      },
      {
        "reference": "Row"
      }
    ],
    "params": [
      {
        "type": "any",
        "name": "props",
        "description": "The props of the column component"
      },
      {
        "type": "Element",
        "name": "children",
        "description": "The child component of the column. This is required"
      },
      {
        "type": "StyleSheet",
        "name": "style",
        "description": "The additional styles to be added to the column. Default is null"
      },
      {
        "type": "boolean",
        "name": "border",
        "description": "The border of the column. Default is false"
      },
      {
        "type": "string",
        "name": "borderType",
        "description": "The border type of the column. Default is solid. Options are: solid, dotted, dashed"
      },
      {
        "type": "string",
        "name": "borderColor",
        "description": "The border color of the column. Default is the text color of the current theme"
      },
      {
        "type": "number",
        "name": "span",
        "description": "The number of columns to span. Default is 1"
      }
    ]
  },
  {
    "title": "ZenDividerProps",
    "description": "Props for the ZenDivider component.",
    "category": "Structure Components Props"
  },
  {
    "title": "ZenDivider",
    "description": "Component to create a customizable divider line.",
    "category": "Structure Components",
    "author": "Danilo Ramírez Mattey",
    "version": "1.0.0",
    "example": [
      {
        "lang": "tsx",
        "code": "import {  Layout, Screen, ZenText, ZenDivider } from 'react-zen-ui';\n\n export default function DividerScreen() {\n     return (\n     <>\n         <Screen useTopSafeArea={false}>\n             <Layout scrollable={true}>\n                 <ZenText type={'p'} paragraph={true} align={'justify'}>\n                   Sometimes you just need a divider for your content. Here are some\n                   examples of how to use the ZenDivider component in different styles\n                   and types.\n                 </ZenText>\n                 <ZenDivider type={'primary'} />\n                 <ZenText type={'h6'} paragraph={true} align={'justify'}>\n                   Another text divided from the one above\n                 </ZenText>\n                 <ZenDivider type={'secondary'} />\n                 <ZenText type={'h5'} paragraph={true} align={'justify'}>\n                    Another text\n                 </ZenText>\n                 <ZenDivider type={'danger'} />\n                 <ZenText type={'h4'} paragraph={true} align={'justify'}>\n                    Another text\n                 </ZenText>\n                 <ZenDivider type={'warning'} />\n                 <ZenText type={'h3'} paragraph={true} align={'justify'}>\n                    Another text\n                 </ZenText>\n                 <ZenDivider type={'info'} />\n                 <ZenText type={'h2'} paragraph={true} align={'justify'}>\n                    Another text\n                 </ZenText>\n             </Layout>\n         </Screen>\n     </>\n     );\n }",
        "closeLang": "tsx"
      }
    ],
    "params": [
      {
        "type": "string",
        "name": "type",
        "description": "The theme type for the divider color. Supports primary, secondary, success, danger, warning, info."
      },
      {
        "type": "number",
        "name": "opacity",
        "description": "The opacity of the divider line. Default is 0.3."
      },
      {
        "type": "number",
        "name": "thickness",
        "description": "The thickness of the divider line in pixels. Default is 2."
      },
      {
        "type": "number",
        "name": "marginFactor",
        "description": "Factor to multiply the standard layout space for top and bottom margins. Default is 0.5."
      }
    ]
  },
  {
    "title": "ZenSpaceBlockProps",
    "description": "Props for the ZenSpaceBlock component.",
    "category": "Structure Components Props",
    "author": "Danilo Ramírez Mattey",
    "version": "1.0.0"
  },
  {
    "title": "ZenSpaceBlock",
    "description": "A simple component that adds vertical space based on a factor of the standard layout space.",
    "category": "Structure Components",
    "author": "Danilo Ramírez Mattey",
    "version": "1.0.0",
    "see": [
      {
        "reference": "ZenDivider"
      }
    ],
    "params": [
      {
        "type": "number",
        "name": "factor",
        "description": "The factor to multiply the standard layout space. Default is 2."
      }
    ]
  },
  {
    "title": "ZenButtonProps",
    "description": "Props for the ZenButton component.",
    "category": "Themed Components Props"
  },
  {
    "title": "ZenButton",
    "description": "A simple button component that can be used throughout the app. It supports different types (primary, secondary, success, info, warning, danger) and all of them are styled according to the current theme. The text color will be automatically selected based on the brightness of the button color, but it can be overwritten by passing a textColor prop.",
    "category": "Themed Components",
    "author": "Danilo Ramírez Mattey",
    "version": "1.0.0",
    "link": [
      {
        "url": "https://github.com/danilor/zen-ui"
      },
      {
        "url": "https://github.com/danilor/zen-ui/blob/main/example/src/components/examples/ButtonExample.tsx"
      }
    ],
    "example": [
      {
        "lang": "tsx",
        "code": "import { ZenButton } from 'react-zen-ui';\r\n import { View } from 'react-native';\r\n\r\n  export default function App(){\r\n    return (\r\n      <View style={{ padding: 20 }}>\r\n        <ZenButton\r\n          title=\"Click Me\"\r\n          type=\"primary\"\r\n          onPress={() => alert('Button Pressed!')}\r\n          leftIcon=\"yoga\"\r\n          rightIcon=\"bonfire\"\r\n        />\r\n      </View>\r\n    );\r\n }",
        "closeLang": "tsx"
      }
    ],
    "params": [
      {
        "type": "string",
        "name": "title",
        "description": "The title of the button"
      },
      {
        "type": "string",
        "name": "type",
        "description": "The type of the button. Can be 'primary', 'secondary', 'success', 'info', 'warning', or 'danger'. Default is 'primary'."
      },
      {
        "type": "string",
        "name": "textColor",
        "description": "The color of the button text. If not provided, it will be automatically selected based on the button color."
      },
      {
        "type": "boolean",
        "name": "fill",
        "description": "Whether the button should fill the width of its container. Default is true."
      },
      {
        "type": "number",
        "name": "touchableOpacity",
        "description": "The opacity of the button when pressed. Default is 0.7."
      },
      {
        "type": "function",
        "name": "pressAction",
        "description": "Alias for pressAction"
      },
      {
        "type": "function",
        "name": "onPress",
        "description": "onPress action"
      },
      {
        "type": "function",
        "name": "longPressAction",
        "description": "Alias for longPressAction"
      },
      {
        "type": "function",
        "name": "onLongPress",
        "description": "onLongPress action"
      },
      {
        "type": "string",
        "name": "leftIcon",
        "description": "The left icon of the button. Should be a valid icon name from the ZenIcon component."
      },
      {
        "type": "string",
        "name": "rightIcon",
        "description": "The right icon of the button. Should be a valid icon name from the ZenIcon component."
      },
      {
        "type": "Element",
        "name": "leftAccessory",
        "description": "A left accessory. Accepts any valid React Node."
      },
      {
        "type": "Element",
        "name": "rightAccessory",
        "description": "A right accessory. Accepts any valid React Node."
      },
      {
        "type": "boolean",
        "name": "disabled",
        "description": "Whether the button is disabled. Default is false."
      },
      {
        "type": "StyleSheet",
        "name": "style",
        "description": "Additional styles for the button container."
      }
    ]
  },
  {
    "title": "ZenCheckProps",
    "description": "Props for the ZenCheck component.",
    "category": "Themed Components Props"
  },
  {
    "title": "ZenCheck",
    "description": "A simple checkbox component that can be used throughout the app. It supports different types (primary, secondary, success, info, warning, danger) and all of them are styled according to the current theme. The checkbox can be positioned to the left or right of the label.",
    "category": "Themed Components",
    "author": "Danilo Ramírez Mattey",
    "version": "1.0.0",
    "params": [
      {
        "type": "string",
        "name": "type",
        "description": "The type of the checkbox. Can be 'primary', 'secondary', 'success', 'info', 'warning', or 'danger'. Default is 'primary'."
      },
      {
        "type": "string",
        "name": "label",
        "description": "The label of the checkbox."
      },
      {
        "type": "string",
        "name": "value",
        "description": "The initial value of the checkbox. Default is false."
      },
      {
        "type": "string",
        "name": "position",
        "description": "The position of the checkbox relative to the label. Can be 'left' or 'right'. Default is 'left'."
      },
      {
        "type": "function",
        "name": "onChange",
        "description": "The function to call when the value of the checkbox changes."
      },
      {
        "type": "StyleSheet",
        "name": "style",
        "description": "Additional styles for the checkbox container."
      },
      {
        "type": "boolean",
        "name": "useBackground",
        "description": "Whether to use a background color for the checkbox icon. Default is false."
      },
      {
        "type": "boolean",
        "name": "disabled",
        "description": "Whether the checkbox is disabled. Default is false."
      }
    ]
  },
  {
    "title": "ZenCode",
    "description": "A simple code block component that can be used to display code snippets throughout the app. It styles the code block according to the current theme.",
    "category": "Themed Components",
    "author": "Danilo Ramírez Mattey",
    "version": "1.0.0",
    "params": [
      {
        "type": "string",
        "name": "content",
        "description": "The code content to display"
      },
      {
        "type": "number",
        "name": "light",
        "description": "A value to lighten or darken the background color. Default is -0.1 (slightly darker)."
      }
    ]
  },
  {
    "title": "ZenIconProps",
    "description": "Props for the ZenIcon component.",
    "category": "Themed Components Props"
  },
  {
    "title": "ZenIcon",
    "description": "A simple icon component that will adapt to the current theme and display the provided icon. If you want to overwrite the color, you can provide a color prop to change it. By default, the icon will adjust to the text color, size and format of the current theme.",
    "category": "Themed Components",
    "author": "Danilo Ramírez Mattey",
    "version": "1.0.0",
    "example": [
      {
        "lang": "tsx",
        "code": "import { ZenIcon } from 'react-zen-ui';\n\nexport default function ExampleComponent(){\n  return (\n    <ZenIcon\n      name={'home'}\n      size={32}\n      color={'#ff0000'}\n      onPress={() => alert('Icon pressed!')}\n    />\n  );\n}",
        "closeLang": "tsx"
      }
    ],
    "see": [
      {
        "reference": "ZenText"
      },
      {
        "reference": "ZenIconButton"
      }
    ],
    "params": [
      {
        "type": "string",
        "name": "name",
        "description": "The icon we want to use"
      },
      {
        "type": "StyleSheet",
        "name": "style",
        "description": "Additional styles for the icon"
      },
      {
        "type": "number",
        "name": "size",
        "description": "Number The size of the icon"
      },
      {
        "type": "string",
        "name": "color",
        "description": "The Color of the Icon. Default to text color of the theme"
      },
      {
        "type": "function",
        "name": "onPress",
        "description": "onPress action"
      },
      {
        "type": "boolean",
        "name": "disabled",
        "description": "Whether the icon is disabled. Default is false."
      }
    ]
  },
  {
    "title": "ZenIconButtonType",
    "description": "Type definition for the ZenIconButton component props.",
    "category": "Themed Components Props"
  },
  {
    "title": "ZenIconButton",
    "description": "A button component that displays an icon and handles press and long-press actions with customizable styles and themes.",
    "category": "Themed Components",
    "author": "Danilo Ramírez Mattey",
    "version": "1.0.0",
    "example": [
      {
        "lang": "tsx",
        "code": "import {\n Column,\n Layout,\n Row,\n Screen,\n Table,\n ZenIconButton,\n ZenText,\n } from 'react-zen-ui';\n import { StyleSheet } from 'react-native';\n\n export default function IconButtonsScreen() {\n     const styles = StyleSheet.create({\n        column: { justifyContent: 'center', alignItems: 'center' },\n     });\n\n     return (\n     <>\n         <Screen useTopSafeArea={false}>\n             <Layout scrollable={true}>\n                 <ZenText type={'p'} paragraph={true} align={'justify'}>\n                   Buttons can be also used with icons only. These are called Icon\n                   Buttons. They can be used in toolbars or action bars to represent\n                   actions with icons only. They can be primary, secondary, warning,\n                   info or danger types.\n                 </ZenText>\n\n                 <Table>\n                     <Row>\n                         <Column style={styles.column}>\n                         <    ZenIconButton icon={'home'} />\n                         </Column>\n                         <Column style={styles.column}>\n                            <ZenIconButton icon={'bell'} type={'secondary'} />\n                         </Column>\n                         <Column style={styles.column}>\n                            <ZenIconButton icon={'dns'} type={'danger'} />\n                         </Column>\n                         <Column style={styles.column}>\n                            <ZenIconButton icon={'eye'} type={'info'} />\n                         </Column>\n                         <Column style={styles.column}>\n                            <ZenIconButton icon={'google-circle'} type={'warning'} />\n                         </Column>\n                     </Row>\n\n                 </Table>\n             </Layout>\n         </Screen>\n     </>\n     );\n }",
        "closeLang": "tsx"
      }
    ],
    "see": [
      {
        "reference": "ZenIcon"
      },
      {
        "reference": "ZenButton"
      }
    ],
    "params": [
      {
        "type": "string",
        "name": "icon",
        "description": "The name of the icon to display."
      },
      {
        "type": "string",
        "name": "type",
        "description": "The theme type for the button (e.g., 'primary', 'secondary')."
      },
      {
        "type": "number",
        "name": "size",
        "description": "The size of the button ('small', 'medium', 'large')."
      },
      {
        "type": "number",
        "name": "touchableOpacity",
        "description": "The opacity of the button when pressed."
      },
      {
        "type": "boolean",
        "name": "disabled",
        "description": "Whether the button is disabled."
      },
      {
        "type": "StyleSheet",
        "name": "style",
        "description": "Additional styles for the button."
      },
      {
        "type": "function",
        "name": "pressAction",
        "description": "Function to execute on button press."
      },
      {
        "type": "function",
        "name": "onPress",
        "description": "Additional function to execute on button press."
      },
      {
        "type": "function",
        "name": "longPressAction",
        "description": "Function to execute on button long press."
      },
      {
        "type": "function",
        "name": "onLongPress",
        "description": "Additional function to execute on button long press."
      },
      {
        "type": "number",
        "name": "opacity",
        "description": "The overall opacity of the button."
      }
    ]
  },
  {
    "title": "ZenInputProps",
    "description": "Props for the ZenInput component.",
    "category": "Themed Components Props"
  },
  {
    "title": "ZenInput",
    "description": "An input field with a label. The label is optional.",
    "category": "Themed Components",
    "author": "Danilo Ramírez Mattey",
    "version": "1.0.0",
    "link": [
      {
        "url": "https://reactnative.dev/docs/textinput"
      }
    ],
    "example": [
      {
        "lang": "tsx",
        "code": "import { ZenButton, ZenInput } from 'react-zen-ui';\n import { useState } from 'react';\n import { StyleSheet, View } from 'react-native';\n\n const styles = StyleSheet.create({\n     buttonsContainer: {\n         display: 'flex',\n         flexDirection: 'row',\n         alignItems: 'center',\n         justifyContent: 'space-between',\n         marginBottom: 20,\n         marginTop: 10,\n         gap: 10,\n     },\n     container: {\n        flex: 1,\n     },\n     box: {\n         width: 60,\n         height: 60,\n         marginVertical: 20,\n     },\n });\n\n export default function InputExample(){\n\n     const [leftAccessory, setLeftAccessory] = useState<boolean>(true);\n     const [rightAccessory, setRightAccessory] = useState<boolean>(true);\n     const [textValue, setTextValue] = useState('Welcome to ZenUI');\n     const [textareaValue, setTextareaValue] = useState('This is a multiline textarea.');\n\n     return (\n         <>\n             <ZenText type={'h4'} paragraph={true} align={'left'}>\n                Input\n             </ZenText>\n             <ZenInput\n                 leftIcon={leftAccessory ? 'user-circle' : undefined}\n                 rightIcon={rightAccessory ? 'check-circle' : undefined}\n                 label={'Single Input'}\n                 onChangeText={(t: string) => setTextValue(t)}\n                 value={textValue}\n                 autoComplete={'off'}\n                 autoCapitalize={'none'}\n                 multiline={false}\n             />\n             <ZenInput\n                 leftIcon={leftAccessory ? 'user-circle' : undefined}\n                 rightIcon={rightAccessory ? 'closed-captions-tag' : undefined}\n                 label={'Multiline Textarea'}\n                 onChangeText={(t: string) => setTextareaValue(t)}\n                 value={textareaValue}\n                 autoComplete={'off'}\n                 autoCapitalize={'none'}\n                 multiline={true}\n             />\n             <ZenInput\n                 leftIcon={leftAccessory ? 'key' : undefined}\n                 rightIcon={rightAccessory ? 'closet' : undefined}\n                 label={'Password Input'}\n                 onChangeText={(t: string) => setPasswordValue(t)}\n                 value={passwordValue}\n                 autoComplete={'off'}\n                 placeholder={''}\n                 autoCapitalize={'none'}\n                 secureTextEntry={true}\n                 multiline={false}\n             />\n\n         </>\n     );\n }",
        "closeLang": "tsx"
      }
    ],
    "params": [
      {
        "type": "string",
        "name": "label",
        "description": "The label for the input field"
      },
      {
        "type": "string",
        "name": "dir",
        "description": "The direction of the text. Can be 'ltr' or 'rtl'. Default is 'ltr'"
      },
      {
        "type": "string",
        "name": "leftIcon",
        "description": "The left icon name"
      },
      {
        "type": "string",
        "name": "rightIcon",
        "description": "The right icon name"
      },
      {
        "type": "Element",
        "name": "leftAccessory",
        "description": "The left accessory element"
      },
      {
        "type": "Element",
        "name": "rightAccessory",
        "description": "The right accessory element"
      },
      {
        "type": "boolean",
        "name": "multiline",
        "description": "Whether the input is multiline"
      },
      {
        "type": "number",
        "name": "multilineVariantHeight",
        "description": "The height multiplier for multiline inputs. Default is 10"
      },
      {
        "type": "boolean",
        "name": "disabled",
        "description": "Whether the input is disabled"
      },
      {
        "type": "Object",
        "name": "props",
        "description": "All regular TextInput props"
      }
    ]
  },
  {
    "title": "ZenListItem",
    "description": "A list item component that can display a title, description, image, and right accessory.",
    "category": "Themed Components",
    "author": "Danilo Ramírez Mattey",
    "version": "1.0.0",
    "example": [
      {
        "lang": "tsx",
        "code": "import {\n   Layout,\n   Screen,\n   ZenIcon,\n   ZenListItem,\n   ZenSpaceBlock,\n   ZenText,\n } from 'react-zen-ui';\n import { useState } from 'react';\n\n export default function ListScreen() {\n   const [currentTime] = useState(new Date().toLocaleTimeString());\n   const [currentDate] = useState(new Date().toLocaleDateString());\n\n   return (\n     <>\n     <Screen useTopSafeArea={false}>\n         <Layout scrollable={true}>\n\n\n         <ZenListItem title={'Item 1'} />\n         <ZenListItem\n         title={'Item 2 with description'}\n         description={'Description'}\n         rightText={currentTime}\n         />\n\n         <ZenListItem\n         title={'Item 3 with image'}\n         description={'Image will be at the left'}\n         imageSource={{ uri: 'https://picsum.photos/100' }}\n         />\n\n         </Layout>\n     </Screen>\n     </>\n   );\n }",
        "closeLang": "tsx"
      }
    ],
    "see": [
      {
        "reference": "ZenIcon"
      },
      {
        "reference": "ZenText"
      }
    ],
    "params": [
      {
        "type": "string",
        "name": "title",
        "description": "The title of the list item."
      },
      {
        "type": "string",
        "name": "description",
        "description": "The description of the list item."
      },
      {
        "type": "string",
        "name": "type",
        "description": "The theme type of the list item."
      },
      {
        "type": "ImageSource",
        "name": "imageSource",
        "description": "The source of the image to be displayed on the left side of the list item."
      },
      {
        "type": "number",
        "name": "height",
        "description": "The height of the list item."
      },
      {
        "type": "string",
        "name": "backColor",
        "description": "The background color of the list item."
      },
      {
        "type": "Function",
        "name": "onPress",
        "description": "The function to be called when the list item is pressed."
      },
      {
        "type": "boolean",
        "name": "disabled",
        "description": "Whether the list item is disabled."
      },
      {
        "type": "string",
        "name": "rightText",
        "description": "The text to be displayed on the right side of the list item."
      },
      {
        "type": "Element",
        "name": "rightAccessory",
        "description": "The accessory component to be displayed on the right side of the list item."
      },
      {
        "type": "boolean",
        "name": "bordered",
        "description": "Whether the list item has a border."
      },
      {
        "type": "boolean",
        "name": "squared",
        "description": "Whether the list item has squared corners."
      },
      {
        "type": "number",
        "name": "spacing",
        "description": "The spacing between list items."
      }
    ]
  },
  {
    "title": "ZenLoadingProps",
    "description": "Props for the ZenLoading component.",
    "category": "Themed Components Props"
  },
  {
    "title": "ZenLoading",
    "description": "A loading indicator using an animated icon. You can set the size to small, medium or large.",
    "category": "Themed Components",
    "version": "1.0.0",
    "example": [
      {
        "lang": "tsx",
        "code": "import { Column, ZenLoading, ZenText, Table, Row } from 'react-zen-ui';\n\n\n export default function LoadingExample(){\n     return (\n         <>\n             <ZenText type={'h4'} paragraph={true} align={'left'}>\n             Loading\n             </ZenText>\n             <Table>\n                 <Row>\n                     <Column>\n                        <ZenLoading size={'large'} />\n                     </Column>\n                     <Column>\n                        <ZenLoading size={'small'} />\n                     </Column>\n                     <Column>\n                        <ZenLoading size={'large'} duration={1000} />\n                     </Column>\n                     <Column>\n                        <ZenLoading size={'small'} duration={1000} />\n                     </Column>\n                 </Row>\n             </Table>\n         </>\n     );\n }",
        "closeLang": "tsx"
      }
    ],
    "see": [
      {
        "reference": "ZenIcon"
      }
    ],
    "params": [
      {
        "type": "number",
        "name": "size",
        "description": "The size of the loading indicator. Can be 'small', 'large' or a number. Default is 'small'"
      },
      {
        "type": "string",
        "name": "color",
        "description": "The color of the loading indicator. Default is the text color of the current theme"
      },
      {
        "type": "number",
        "name": "duration",
        "description": "The duration of one full rotation in milliseconds. Default is 1500ms"
      }
    ]
  },
  {
    "see": [
      {
        "reference": "ZenInput"
      }
    ]
  },
  {
    "title": "ZenSelect",
    "description": "A select component with a label. The label is optional. Based on ZenInput.",
    "category": "Themed Components",
    "author": "Danilo Ramírez Mattey",
    "version": "1.0.0",
    "see": [
      {
        "reference": "ZenInput"
      }
    ],
    "params": [
      {
        "type": "string[]",
        "name": "items",
        "description": "The list of items to select from. This is required"
      },
      {
        "type": "string",
        "name": "label",
        "description": "The label for the select component"
      },
      {
        "type": "string",
        "name": "placeholder",
        "description": "The placeholder for the select component"
      },
      {
        "type": "string",
        "name": "dir",
        "description": "The direction of the text. Can be 'ltr' or 'rtl'. Default is 'ltr'"
      },
      {
        "type": "string",
        "name": "leftIcon",
        "description": "The left icon name"
      },
      {
        "type": "Element",
        "name": "leftAccessory",
        "description": "The left accessory element"
      },
      {
        "type": "boolean",
        "name": "disabled",
        "description": "Whether the select is disabled"
      },
      {
        "type": "string",
        "name": "type",
        "description": "The theme type for the select. Default is 'primary'"
      },
      {
        "type": "string",
        "name": "defaultValue",
        "description": "The default selected value"
      },
      {
        "type": "Function",
        "name": "onChange",
        "description": "Callback function when the selected item changes"
      },
      {
        "type": "number",
        "name": "maxNumberOfVisibleItems",
        "description": "The maximum number of items to show when the select is opened. Default is 3"
      }
    ]
  },
  {
    "title": "ZenTextProps",
    "description": "Props for the ZenText component.",
    "category": "Themed Components Props"
  },
  {
    "title": "ZenText",
    "description": "The most basic text component that will adapt to the current theme",
    "params": [
      {
        "type": "Element",
        "name": "children",
        "description": "The text content to be displayed within the ZenText component."
      },
      {
        "type": "StyleSheet",
        "name": "style",
        "description": "Additional styles to customize the appearance of the text."
      },
      {
        "type": "number",
        "name": "size",
        "description": "The size of the text. Can be 'small', 'medium', 'large' or a number."
      },
      {
        "type": "string",
        "name": "type",
        "description": "The type of text style to apply. Options are 'h1', 'h2', 'h3', 'h4', 'h5', 'h6', 'p', 'small'."
      },
      {
        "type": "string",
        "name": "align",
        "description": "The alignment of the text. Options are 'left', 'center', 'right', 'justify'."
      },
      {
        "type": "boolean",
        "name": "paragraph",
        "description": "Whether to add margin to the top and bottom of the text to separate it as a paragraph."
      },
      {
        "type": "string",
        "name": "textColor",
        "description": "The color of the text. Defaults to the text color of the current theme."
      },
      {
        "type": "boolean",
        "name": "fill",
        "description": "Whether the text should take the full width of its container."
      }
    ]
  },
  {
    "title": "ZenImageSliderItem",
    "description": "Props for each item in ZenImageSlider component.",
    "category": "Widget Components Props",
    "author": "Danilo Ramírez Mattey",
    "version": "1.0.0"
  },
  {
    "title": "ZenImageSliderProps",
    "description": "Props for ZenImageSlider component.",
    "category": "Widget Components Props",
    "author": "Danilo Ramírez Mattey",
    "version": "1.0.0"
  },
  {
    "title": "ZenImageSlider",
    "description": "A simple image slider component with pagination.",
    "category": "Widget Components",
    "author": "Danilo Ramírez Mattey",
    "version": "1.0.0",
    "example": [
      {
        "lang": "tsx",
        "code": "import {\n  Layout,\n  Screen,\n  ZenImageSlider,\n  type ZenImageSliderItem,\n  ZenSpaceBlock,\n} from 'react-zen-ui';\n\nexport default function SliderScreen() {\n  const imageBase = 'https://picsum.photos/600?';\n  const images: ZenImageSliderItem[] = [\n    {source:{uri:imageBase + Math.random().toString()}, title: 'Image with Text'},\n    {source:{uri:imageBase + Math.random().toString()}},\n    {source:{uri:imageBase + Math.random().toString()} , title: 'Another Image with Text'},\n    {source:{uri:imageBase + Math.random().toString()}},\n    {source:{uri:imageBase + Math.random().toString()}, onPress: ()=>{}, title:'This image supports onPress action'},\n  ];\n  return (\n    <>\n      <Screen useTopSafeArea={false}>\n        <Layout scrollable={true}>\n          <ZenSpaceBlock />\n          <ZenImageSlider images={images} />\n        </Layout>\n      </Screen>\n    </>\n  );\n}",
        "closeLang": "tsx"
      }
    ],
    "params": [
      {
        "type": "ZenImageSliderItem[]",
        "name": "images",
        "description": "Array of images to display. Each image can have a source, optional onPress action, and optional title. Format: { source: any; onPress?: () => void; title?: string; }"
      },
      {
        "type": "string",
        "name": "type",
        "description": "Theme type"
      },
      {
        "type": "number",
        "name": "ratio",
        "description": "Aspect ratio (width / height)"
      },
      {
        "type": "boolean",
        "name": "pagination",
        "description": "Show pagination dots"
      },
      {
        "type": "number",
        "name": "paginationRelationToImage",
        "description": "Size of pagination dots in relation to image width"
      },
      {
        "type": "boolean",
        "name": "bordered",
        "description": "Show border around the slider"
      }
    ]
  },
  {
    "title": "ZenPlay",
    "description": "A play button component overlayed on an image, with optional left text and right icon.",
    "category": "Widget Components",
    "author": "Danilo Ramírez Mattey",
    "version": "1.0.0",
    "example": [
      {
        "lang": "tsx",
        "code": "import {\n  Layout,\n  Screen,\n  ZenPlay,\n  } from 'react-zen-ui';\n  import { StyleSheet } from 'react-native';\n\n  export default function PlayScreen() {\n      const styles = StyleSheet.create({\n        play: {\n          width: 200,\n          height: 200,\n        },\n      });\n\n      const handlePlayPress = () => {\n        console.log('Play button pressed!');\n      };\n\n      return (\n        <>\n          <Screen useTopSafeArea={false}>\n            <Layout centerContent={true}>\n              <ZenPlay\n                style={styles.play}\n                imageSource={{\n                  uri: 'https://example.com/image.jpg',\n                }}\n                onPress={handlePlayPress}\n                icon={'play'}\n                leftText={'Sample Text'}\n                rightIcon={'info'}\n              />\n            </Layout>\n          </Screen>\n        </>\n      );\n  }",
        "closeLang": "tsx"
      }
    ],
    "params": [
      {
        "type": "string",
        "name": "type",
        "description": "The theme type for the component (e.g., 'primary', 'secondary')."
      },
      {
        "type": "ImageSource",
        "name": "imageSource",
        "description": "The source of the image to display."
      },
      {
        "type": "StyleSheet",
        "name": "style",
        "description": "Additional styles for the component container."
      },
      {
        "type": "Function",
        "name": "onPress",
        "description": "Function to execute when the play button is pressed."
      },
      {
        "type": "string",
        "name": "icon",
        "description": "The name of the icon to display on the play button."
      },
      {
        "type": "string",
        "name": "leftText",
        "description": "Optional text to display at the bottom left of the image."
      },
      {
        "type": "boolean",
        "name": "bordered",
        "description": "Whether to display a border around the component. Default is false."
      }
    ]
  },
  {
    "title": "ZenProfileProps",
    "description": "Props for the ZenProfile component.",
    "category": "Widget Components Props"
  },
  {
    "title": "ZenProfile",
    "description": "A profile component that displays a banner image, an avatar image, a title, a subtitle element, a description, and a footer. The avatar image is positioned overlapping the banner image. The component is styled according to the current theme and supports different types (primary, secondary, success, info, warning, danger).",
    "category": "Widget Components",
    "author": "Danilo Ramírez Mattey",
    "version": "1.0.0",
    "group": "Widgets",
    "example": [
      {
        "lang": "tsx",
        "code": "import {\n Layout,\n Screen, ZenButton,\n ZenIcon,\n ZenIconButton,\n ZenSpaceBlock,\n } from 'react-zen-ui';\n import { ZenProfile } from 'react-zen-ui';\n import { StyleSheet, View } from 'react-native';\n\n export default function ProfileScreen() {\n\n     const styles = StyleSheet.create({\n         container: {\n            flexDirection: 'row', gap: 10, alignItems: 'center'\n         }\n     });\n\n     return (\n         <>\n             <Screen useTopSafeArea={false}>\n                 <Layout scrollable={true}>\n                     <ZenSpaceBlock />\n                     <ZenProfile\n                         bannerImageSource={{\n                            uri: 'https://picsum.photos/1000?' + Math.random().toString(36),\n                         }}\n                         avatarImageSource={{\n                            uri: 'https://picsum.photos/id/237/500/500',\n                         }}\n                         title={'Lucky Dog'.toUpperCase()}\n                         subTitleElement={\n                             <View\n                                style={styles.container}\n                             >\n                                 <ZenIcon name={'star'} color={'yellow'} />\n                                 <ZenIcon name={'star'} color={'yellow'} />\n                                 <ZenIcon name={'star'} color={'yellow'} />\n                                 <ZenIcon name={'star'} color={'yellow'} />\n                                 <ZenIcon name={'star'} />\n                             </View>\n                         }\n                         description={\n                            'A friendly dog who loves to play and cuddle with everyone he meets. He is always up for an adventure and enjoys exploring new places.'\n                         }\n                         footer={\n                             <View\n                                 style={styles.container}\n                             >\n                                 <ZenIconButton icon={'facebook'} onPress={()=> null} />\n                             </View>\n                         }\n                     />\n                 </Layout>\n             </Screen>\n         </>\n     );\n }",
        "closeLang": "tsx"
      }
    ],
    "see": [
      {
        "reference": "ZenButton"
      },
      {
        "reference": "ZenIconButton"
      },
      {
        "reference": "ZenIcon"
      },
      {
        "reference": "ZenText"
      }
    ],
    "params": [
      {
        "type": "string",
        "name": "type",
        "description": "The theme type for the component. Can be 'primary', 'secondary', 'success', 'info', 'warning', or 'danger'. Default is 'primary'."
      },
      {
        "type": "ImageSource",
        "name": "bannerImageSource",
        "description": "The source for the banner image."
      },
      {
        "type": "string",
        "name": "title",
        "description": "The title of the profile."
      },
      {
        "type": "Element|Element[]",
        "name": "subTitleElement",
        "description": "The subtitle element of the profile."
      },
      {
        "type": "boolean",
        "name": "bordered",
        "description": "Whether the avatar and banner images should have borders. Default is true."
      },
      {
        "type": "number",
        "name": "bannerHeight",
        "description": "The height of the banner image. Default is 150."
      },
      {
        "type": "Element|{number",
        "name": "description",
        "description": "The description of the profile."
      },
      {
        "type": "StyleSheet",
        "name": "style",
        "description": "Additional styles for the profile container."
      }
    ]
  },
  {
    "title": "ZenSpotlight",
    "description": "A spotlight component that displays an image with an optional footer and an icon button.",
    "category": "Widget Components",
    "author": "Danilo Ramírez Mattey",
    "version": "1.0.0",
    "group": "Widgets",
    "example": [
      {
        "lang": "tsx",
        "code": "import { Layout, Screen, ZenSpaceBlock, ZenSpotlight } from 'react-zen-ui';\n import {View} from 'react-native';\n\n export default function SpotlightScreen() {\n   return (\n     <>\n       <Screen useTopSafeArea={false}>\n         <Layout scrollable={true}>\n         <ZenSpaceBlock />\n         <ZenSpotlight footerText={'This image was taken from Picsum'} imageSource={{uri:'https://picsum.photos/300?random'}} bordered={true} borderRounded={true} />\n         </Layout>\n       </Screen>\n     </>\n   );\n }",
        "closeLang": "tsx"
      }
    ],
    "see": [
      {
        "reference": "ZenText"
      },
      {
        "reference": "ZenIconButton"
      }
    ],
    "params": [
      {
        "type": "string",
        "name": "title",
        "description": "Optional title to be displayed on top of the image."
      },
      {
        "type": "boolean",
        "name": "titleBackground",
        "description": "Whether the title should have a background for better visibility. Default is false."
      },
      {
        "type": "string",
        "name": "titleType",
        "description": "The text type for the title. Default is 'h3'."
      },
      {
        "type": "ImageSource",
        "name": "imageSource",
        "description": "The source of the image to be displayed."
      },
      {
        "type": "string",
        "name": "footerText",
        "description": "Optional text to be displayed in the footer."
      },
      {
        "type": "string",
        "name": "iconName",
        "description": "The name of the icon to be displayed in the button. Default is 'arrow-right-circle'."
      },
      {
        "type": "string",
        "name": "type",
        "description": "The theme type for the component. Default is 'primary'."
      },
      {
        "type": "boolean",
        "name": "bordered",
        "description": "Whether the image should have a border. Default is false."
      },
      {
        "type": "boolean",
        "name": "borderRounded",
        "description": "Whether the border should be rounded. Default is false."
      },
      {
        "type": "Object",
        "name": "style",
        "description": "Additional styles for the container."
      },
      {
        "type": "Function",
        "name": "onPress",
        "description": "Function to be called when the icon button is pressed."
      }
    ]
  },
  {
    "title": "useDrawer",
    "description": "A custom hook to access the current state of the drawer (open or closed) from the ZenThemeContext. Its call must be made inside the context of a ZenThemeProvider.",
    "category": "Hooks",
    "author": "Danilo Ramírez Mattey",
    "version": "1.0.0",
    "return": [
      {
        "type": "boolean",
        "description": "The current state of the drawer (true for open, false for closed)"
      }
    ],
    "example": [
      {
        "lang": "tsx",
        "code": "import { useDrawer } from 'react-zen-ui';\n\nexport default function DrawerStateComponent(){\n    const isDrawerOpen = useDrawer();\n    return (\n        <div>\n            The drawer is currently {isDrawerOpen ? 'open' : 'closed'}.\n        </div>\n    );\n}",
        "closeLang": "tsx"
      }
    ],
    "see": [
      {
        "reference": "ZenThemeProvider"
      }
    ]
  },
  {
    "title": "useToggleDrawer",
    "description": "A custom hook to toggle the drawer state (open or closed) from the ZenThemeContext. Its call must be made inside the context of a ZenThemeProvider.",
    "category": "Hooks",
    "author": "Danilo Ramírez Mattey",
    "version": "1.0.0",
    "return": [
      {
        "type": "Function",
        "description": "A function to toggle the drawer state"
      }
    ]
  },
  {
    "title": "useTheme",
    "description": "A custom hook to access the current theme from the ZenThemeContext. It will contain all the theme properties defined in the ThemeModel. Its call must be made inside the context of a ZenThemeProvider.",
    "category": "Hooks",
    "author": "Danilo Ramírez Mattey",
    "version": "1.0.0",
    "return": [
      {
        "type": "ThemeModel",
        "description": "The current theme object"
      }
    ],
    "example": [
      {
        "lang": "tsx",
        "code": "import { useTheme } from 'react-zen-ui';\n\nexport default function ThemedComponent(){\n    const theme = useTheme();\n    return (\n        <div style={{backgroundColor: theme.backgroundColor, color: theme.textColor}}>\n            This component is themed!\n        </div>\n    );\n}",
        "closeLang": "tsx"
      }
    ],
    "see": [
      {
        "reference": "ZenThemeProvider"
      }
    ]
  },
  {
    "title": "Intro",
    "description": "ZenUI is a React component library that provides a set of customizable and themeable UI components to help developers build modern mobile applications with ease. It offers a variety of components such as buttons, inputs, icons, and layouts, all designed to be responsive and visually appealing. With ZenUI, developers can quickly create beautiful and functional user interfaces while maintaining consistency across their applications.",
    "category": "Documentation",
    "author": "Danilo Ramírez Mattey"
  },
  {
    "title": "hex2",
    "description": "Convert a number to a two-digit hexadecimal string",
    "category": "Color Utilities",
    "return": [
      {
        "type": "string",
        "description": "The two-digit hexadecimal string"
      }
    ],
    "params": [
      {
        "type": "number",
        "name": "c",
        "description": "The number to convert"
      }
    ]
  },
  {
    "title": "color",
    "description": "Create a hex color string from RGB values",
    "category": "Color Utilities",
    "return": [
      {
        "type": "string",
        "description": "The hex color string"
      }
    ],
    "params": [
      {
        "type": "number",
        "name": "r",
        "description": "The red factor (0-255)"
      },
      {
        "type": "number",
        "name": "g",
        "description": "The green factor (0-255)"
      },
      {
        "type": "number",
        "name": "b",
        "description": "The blue factor (0-255)"
      }
    ]
  },
  {
    "title": "shade",
    "description": "Shade a hex color by a given light factor",
    "category": "Color Utilities",
    "return": [
      {
        "type": "string",
        "description": "The shaded hex color"
      }
    ],
    "params": [
      {
        "type": "string",
        "name": "col",
        "description": "The hex color to shade"
      },
      {
        "type": "number",
        "name": "light",
        "description": "The light factor (-1 to 1). Negative values darken the color, positive values lighten it."
      }
    ]
  },
  {
    "title": "hexToRgb",
    "description": "Convert a hex color string to an RGB object",
    "category": "Color Utilities",
    "return": [
      {
        "type": "string|null",
        "description": "The RGB color string in the format 'rgba(r, g, b, opacity)' or null if the hex string is invalid"
      }
    ],
    "params": [
      {
        "type": "string",
        "name": "hex",
        "description": "The hex color string"
      },
      {
        "type": "number",
        "name": "opacity",
        "description": "The opacity value (0-1)"
      }
    ]
  },
  {
    "title": "getContrastTextColor",
    "description": "Given a hex color, determine whether black or white text would provide better contrast.",
    "category": "Color Utilities",
    "return": [
      {
        "type": "string",
        "description": "'#000000' for black text or '#ffffff' for white text"
      }
    ],
    "params": [
      {
        "type": "string",
        "name": "hexColor",
        "description": "* @returns {string} '#000000' for black text or '#ffffff' for white text"
      }
    ]
  }
]